actproxy/__init__.py
actproxy-0.2.0.dist-info/entry_points.txt
actproxy-0.2.0.dist-info/LICENSE.md
actproxy-0.2.0.dist-info/WHEEL
actproxy-0.2.0.dist-info/METADATA
actproxy-0.2.0.dist-info/RECORD
