Metadata-Version: 2.1
Name: actproxy
Version: 0.2.0
Summary: Sync & asyncio (Requests & AIOHTTP) proxy rotator + utils for actproxy API & services.
Home-page: https://actproxy.com/aff.php?aff=30
License: MIT
Keywords: python,socks,aiohttp,requests,python3,socks5,proxies,rotate,actproxy
Author: TensorTom
Author-email: 14287229+TensorTom@users.noreply.github.com
Requires-Python: >=3.9,<4.0
Classifier: Development Status :: 4 - Beta
Classifier: Environment :: Console
Classifier: Framework :: AsyncIO
Classifier: License :: OSI Approved :: MIT License
Classifier: Operating System :: OS Independent
Classifier: Programming Language :: Python :: 3
Classifier: Programming Language :: Python :: 3.9
Classifier: Topic :: Internet :: WWW/HTTP
Classifier: Topic :: Software Development :: Libraries :: Python Modules
Classifier: Topic :: System :: Networking
Requires-Dist: aiohttp (>=3.6.3,<4.0.0)
Requires-Dist: aiohttp-socks (>=0.5.5,<0.6.0)
Requires-Dist: kiss-headers (>=2.2.3,<3.0.0)
Requires-Dist: mo-dots (>=3.93.20259,<4.0.0)
Requires-Dist: pytest (>=6.1.1,<7.0.0)
Requires-Dist: pytest-aiohttp (>=0.3.0,<0.4.0)
Requires-Dist: pytest-asyncio (>=0.14.0,<0.15.0)
Requires-Dist: python-socks[asyncio] (>=1.1.0,<2.0.0)
Requires-Dist: requests[socks] (>=2.24.0,<3.0.0)
Requires-Dist: toml (>=0.10.1,<0.11.0)
Requires-Dist: typing_extensions (>=3.7.4,<4.0.0)
Project-URL: Repository, https://github.com/tensortom/actproxy
